fa2_modified/__init__.py
fa2_modified/fa2util.pxd
fa2_modified/fa2util.cpython-310-x86_64-linux-gnu.so
fa2_modified/fa2util.c
fa2_modified/forceatlas2.py
fa2_modified/fa2util.py
fa2_modified-0.3.10.dist-info/WHEEL
fa2_modified-0.3.10.dist-info/LICENSE
fa2_modified-0.3.10.dist-info/top_level.txt
fa2_modified-0.3.10.dist-info/RECORD
fa2_modified-0.3.10.dist-info/METADATA
