Metadata-Version: 2.1
Name: fa2_modified
Version: 0.3.10
Summary: The fastest ForceAtlas2 algorithm for Python (and NetworkX)
Home-page: https://github.com/AminAlam/forceatlas2_maintained
Author: Bhargav Chippada, Amin Alam
Keywords: forceatlas2,networkx,force-directed-graph,force-layout,graph
Classifier: Development Status :: 5 - Production/Stable
Classifier: Intended Audience :: Science/Research
Classifier: Topic :: Scientific/Engineering :: Mathematics
Classifier: License :: OSI Approved :: GNU General Public License v3 (GPLv3)
Classifier: Programming Language :: Python :: 2
Classifier: Programming Language :: Python :: 3
License-File: LICENSE
Requires-Dist: numpy
Requires-Dist: scipy
Requires-Dist: tqdm
Provides-Extra: igraph
Requires-Dist: python-igraph ; extra == 'igraph'
Provides-Extra: networkx
Requires-Dist: networkx ; extra == 'networkx'
